LICENSE
hartware_lib/__init__.py
hartware_lib/adapters/__init__.py
hartware_lib/adapters/async_http.py
hartware_lib/adapters/filesystem.py
hartware_lib/adapters/hartware.py
hartware_lib/adapters/http_rpc.py
hartware_lib/adapters/rabbitmq.py
hartware_lib/adapters/slack.py
hartware_lib/commands/__init__.py
hartware_lib/commands/slack.py
hartware_lib/logging.py
hartware_lib/py.typed
hartware_lib/serializers/__init__.py
hartware_lib/serializers/builders.py
hartware_lib/serializers/dataclasses.py
hartware_lib/serializers/main.py
hartware_lib/serializers/pandas.py
hartware_lib/settings.py
hartware_lib/types.py
hartware_lib/utils/__init__.py
hartware_lib/utils/casing.py
hartware_lib/utils/datetime.py
hartware_lib-0.5.38.dist-info/LICENSE
hartware_lib-0.5.38.dist-info/METADATA
hartware_lib-0.5.38.dist-info/WHEEL
hartware_lib-0.5.38.dist-info/entry_points.txt
hartware_lib-0.5.38.dist-info/RECORD
